token_service/__init__.py
token_service/token_service.py
token_service-0.1.7.dist-info/licenses/LICENSE
token_service-0.1.7.dist-info/METADATA
token_service-0.1.7.dist-info/WHEEL
token_service-0.1.7.dist-info/top_level.txt
token_service-0.1.7.dist-info/RECORD
